{"http://rdfs.org/ns/void#inDataset": ["http://www.semwebtech.org/mondial/md_dataset"], "http://www.opengis.net/ont/geosparql#hasMetricArea": ["117000"], "http://www.opengis.net/ont/geosparql#hasMetricLength": ["1013"], "http://www.semwebtech.org/mondial/10/meta#flowsInto": ["http://www.semwebtech.org/mondial/seas/Atlantic+Ocean"], "http://www.semwebtech.org/mondial/10/meta#hasEstuary": ["http://www.semwebtech.org/mondial/estuarys/Loire"], "http://www.semwebtech.org/mondial/10/meta#hasSource": ["http://www.semwebtech.org/mondial/sources/Loire"], "http://www.semwebtech.org/mondial/10/meta#locatedIn": ["http://www.semwebtech.org/mondial/countries/F", "http://www.semwebtech.org/mondial/countries/F/provinces/Auvergne-Rh\u00f4ne-Alpes", "http://www.semwebtech.org/mondial/countries/F/provinces/Bourgogne-Franche-Comt\u00e9", "http://www.semwebtech.org/mondial/countries/F/provinces/Centre-Val+de+Loire", "http://www.semwebtech.org/mondial/countries/F/provinces/Pays+de+la+Loire"], "http://www.w3.org/1999/02/22-rdf-syntax-ns#type": ["http://www.semwebtech.org/mondial/10/meta#River"], "http://www.w3.org/2000/01/rdf-schema#label": ["Loire"]}