{"http://rdfs.org/ns/void#inDataset": ["http://www.semwebtech.org/mondial/md_dataset"], "http://www.opengis.net/ont/geosparql#hasGeometry": ["http://www.semwebtech.org/mondial/countries/AND_geom"], "http://www.opengis.net/ont/geosparql#hasMetricArea": ["450"], "http://www.semwebtech.org/mondial/10/meta#capital": ["http://www.semwebtech.org/mondial/countries/AND/cities/Andorra+la+Vella"], "http://www.semwebtech.org/mondial/10/meta#carCode": ["AND"], "http://www.semwebtech.org/mondial/10/meta#gdpAgri": ["14"], "http://www.semwebtech.org/mondial/10/meta#gdpInd": ["79"], "http://www.semwebtech.org/mondial/10/meta#gdpServ": ["6"], "http://www.semwebtech.org/mondial/10/meta#gdpTotal": ["4800"], "http://www.semwebtech.org/mondial/10/meta#government": ["parliamentary democracy that retains as its chiefs of state a co-principality"], "http://www.semwebtech.org/mondial/10/meta#hasCity": ["http://www.semwebtech.org/mondial/countries/AND/cities/Andorra+la+Vella"], "http://www.semwebtech.org/mondial/10/meta#independenceDate": ["1278-09-08"], "http://www.semwebtech.org/mondial/10/meta#infantMortality": ["3.69"], "http://www.semwebtech.org/mondial/10/meta#neighbor": ["http://www.semwebtech.org/mondial/countries/E", "http://www.semwebtech.org/mondial/countries/F"], "http://www.semwebtech.org/mondial/10/meta#populationGrowth": ["0.17"], "http://www.semwebtech.org/mondial/10/meta#unemployment": ["4"], "http://www.w3.org/1999/02/22-rdf-syntax-ns#type": ["http://www.semwebtech.org/mondial/10/meta#Country"], "http://www.w3.org/2000/01/rdf-schema#label": ["Andorra"], "http://www.w3.org/2004/02/skos/core#prefLabel": ["Principat d'Andorra"], "http://www.w3.org/ns/sosa/hasObservation": ["http://www.semwebtech.org/mondial/countries/AND_obeth1", "http://www.semwebtech.org/mondial/countries/AND_obeth2", "http://www.semwebtech.org/mondial/countries/AND_obeth3", "http://www.semwebtech.org/mondial/countries/AND_obeth4", "http://www.semwebtech.org/mondial/countries/AND_obeth5", "http://www.semwebtech.org/mondial/countries/AND_obeth6", "http://www.semwebtech.org/mondial/countries/AND_obpop", "http://www.semwebtech.org/mondial/countries/AND_obpophist0", "http://www.semwebtech.org/mondial/countries/AND_obpophist1", "http://www.semwebtech.org/mondial/countries/AND_obpophist2", "http://www.semwebtech.org/mondial/countries/AND_obpophist3", "http://www.semwebtech.org/mondial/countries/AND_obpophist4", "http://www.semwebtech.org/mondial/countries/AND_obpophist5", "http://www.semwebtech.org/mondial/countries/AND_obpophist6", "http://www.semwebtech.org/mondial/countries/AND_obpophist7", "http://www.semwebtech.org/mondial/countries/AND_obpophist8", "http://www.semwebtech.org/mondial/countries/AND_obrel1", "http://www.semwebtech.org/mondial/countries/AND_obrel2", "http://www.semwebtech.org/mondial/countries/AND_obrel3", "http://www.semwebtech.org/mondial/countries/AND_obrel4", "http://www.semwebtech.org/mondial/countries/AND_obrel5", "http://www.semwebtech.org/mondial/countries/AND_obrel6"]}