{"http://rdfs.org/ns/void#inDataset": ["http://www.semwebtech.org/mondial/md_dataset"], "http://www.semwebtech.org/mondial/10/meta#abbrev": ["SICA"], "http://www.semwebtech.org/mondial/10/meta#established": ["1991-12-13"], "http://www.semwebtech.org/mondial/10/meta#hasHeadq": ["http://www.semwebtech.org/mondial/countries/ES/cities/San+Salvador"], "http://www.w3.org/1999/02/22-rdf-syntax-ns#type": ["http://www.semwebtech.org/mondial/10/meta#Organization"], "http://www.w3.org/2000/01/rdf-schema#label": ["Central American Integration System"], "http://www.w3.org/2000/01/rdf-schema#member": ["http://www.semwebtech.org/mondial/countries/AUS", "http://www.semwebtech.org/mondial/countries/BR", "http://www.semwebtech.org/mondial/countries/BZ", "http://www.semwebtech.org/mondial/countries/CN", "http://www.semwebtech.org/mondial/countries/CR", "http://www.semwebtech.org/mondial/countries/D", "http://www.semwebtech.org/mondial/countries/DOM", "http://www.semwebtech.org/mondial/countries/E", "http://www.semwebtech.org/mondial/countries/ES", "http://www.semwebtech.org/mondial/countries/F", "http://www.semwebtech.org/mondial/countries/GCA", "http://www.semwebtech.org/mondial/countries/HN", "http://www.semwebtech.org/mondial/countries/I", "http://www.semwebtech.org/mondial/countries/J", "http://www.semwebtech.org/mondial/countries/MEX", "http://www.semwebtech.org/mondial/countries/NIC", "http://www.semwebtech.org/mondial/countries/PA", "http://www.semwebtech.org/mondial/countries/PE", "http://www.semwebtech.org/mondial/countries/RA", "http://www.semwebtech.org/mondial/countries/RCH", "http://www.semwebtech.org/mondial/countries/ROK", "http://www.semwebtech.org/mondial/countries/USA", "http://www.semwebtech.org/mondial/countries/V"]}