{"http://rdfs.org/ns/void#inDataset": ["http://www.semwebtech.org/mondial/md_dataset"], "http://www.opengis.net/ont/geosparql#hasMetricArea": ["346"], "http://www.semwebtech.org/mondial/10/meta#capital": ["http://www.semwebtech.org/mondial/countries/VIRG/cities/Charlotte+Amalie"], "http://www.semwebtech.org/mondial/10/meta#carCode": ["VIRG"], "http://www.semwebtech.org/mondial/10/meta#dependentOf": ["http://www.semwebtech.org/mondial/countries/USA"], "http://www.semwebtech.org/mondial/10/meta#gdpAgri": ["1"], "http://www.semwebtech.org/mondial/10/meta#gdpInd": ["19"], "http://www.semwebtech.org/mondial/10/meta#gdpServ": ["80"], "http://www.semwebtech.org/mondial/10/meta#gdpTotal": ["1200"], "http://www.semwebtech.org/mondial/10/meta#government": ["organized"], "http://www.semwebtech.org/mondial/10/meta#hasCity": ["http://www.semwebtech.org/mondial/countries/VIRG/cities/Charlotte+Amalie"], "http://www.semwebtech.org/mondial/10/meta#infantMortality": ["6.79"], "http://www.semwebtech.org/mondial/10/meta#populationGrowth": ["-0.56"], "http://www.semwebtech.org/mondial/10/meta#unemployment": ["6.2"], "http://www.w3.org/1999/02/22-rdf-syntax-ns#type": ["http://www.semwebtech.org/mondial/10/meta#Country"], "http://www.w3.org/2000/01/rdf-schema#label": ["Virgin Islands"], "http://www.w3.org/ns/sosa/hasObservation": ["http://www.semwebtech.org/mondial/countries/VIRG_obeth1", "http://www.semwebtech.org/mondial/countries/VIRG_obeth2", "http://www.semwebtech.org/mondial/countries/VIRG_obeth3", "http://www.semwebtech.org/mondial/countries/VIRG_obeth4", "http://www.semwebtech.org/mondial/countries/VIRG_obpop", "http://www.semwebtech.org/mondial/countries/VIRG_obpophist0", "http://www.semwebtech.org/mondial/countries/VIRG_obpophist1", "http://www.semwebtech.org/mondial/countries/VIRG_obpophist2", "http://www.semwebtech.org/mondial/countries/VIRG_obpophist3", "http://www.semwebtech.org/mondial/countries/VIRG_obpophist4", "http://www.semwebtech.org/mondial/countries/VIRG_obpophist5", "http://www.semwebtech.org/mondial/countries/VIRG_obpophist6", "http://www.semwebtech.org/mondial/countries/VIRG_obpophist7", "http://www.semwebtech.org/mondial/countries/VIRG_obrel1", "http://www.semwebtech.org/mondial/countries/VIRG_obrel2", "http://www.semwebtech.org/mondial/countries/VIRG_obrel3"]}