{"http://rdfs.org/ns/void#inDataset": ["http://www.semwebtech.org/mondial/md_dataset"], "http://www.opengis.net/ont/geosparql#hasMetricArea": ["23000"], "http://www.opengis.net/ont/geosparql#hasMetricLength": ["592"], "http://www.semwebtech.org/mondial/10/meta#flowsInto": ["http://www.semwebtech.org/mondial/lakes/Kama+Reservoir"], "http://www.semwebtech.org/mondial/10/meta#hasEstuary": ["http://www.semwebtech.org/mondial/estuarys/Chusovaya"], "http://www.semwebtech.org/mondial/10/meta#hasSource": ["http://www.semwebtech.org/mondial/sources/Chusovaya"], "http://www.semwebtech.org/mondial/10/meta#locatedIn": ["http://www.semwebtech.org/mondial/countries/R", "http://www.semwebtech.org/mondial/countries/R/provinces/Chelyabinskaya", "http://www.semwebtech.org/mondial/countries/R/provinces/Permskij", "http://www.semwebtech.org/mondial/countries/R/provinces/Sverdlovskaya"], "http://www.w3.org/1999/02/22-rdf-syntax-ns#type": ["http://www.semwebtech.org/mondial/10/meta#River"], "http://www.w3.org/2000/01/rdf-schema#label": ["Chusovaya"]}