{"http://rdfs.org/ns/void#inDataset": ["http://www.semwebtech.org/mondial/md_dataset"], "http://www.opengis.net/ont/geosparql#hasGeometry": ["http://www.semwebtech.org/mondial/countries/GL_geom"], "http://www.opengis.net/ont/geosparql#hasMetricArea": ["2175600"], "http://www.semwebtech.org/mondial/10/meta#capital": ["http://www.semwebtech.org/mondial/countries/GL/cities/Nuuk"], "http://www.semwebtech.org/mondial/10/meta#carCode": ["GL"], "http://www.semwebtech.org/mondial/10/meta#dependentOf": ["http://www.semwebtech.org/mondial/countries/DK"], "http://www.semwebtech.org/mondial/10/meta#gdpAgri": ["4"], "http://www.semwebtech.org/mondial/10/meta#gdpInd": ["29"], "http://www.semwebtech.org/mondial/10/meta#gdpServ": ["67"], "http://www.semwebtech.org/mondial/10/meta#gdpTotal": ["2160"], "http://www.semwebtech.org/mondial/10/meta#government": ["parliamentary democracy within a constitutional monarchy"], "http://www.semwebtech.org/mondial/10/meta#hasCity": ["http://www.semwebtech.org/mondial/countries/GL/cities/Nuuk"], "http://www.semwebtech.org/mondial/10/meta#infantMortality": ["9.42"], "http://www.semwebtech.org/mondial/10/meta#populationGrowth": ["0.02"], "http://www.semwebtech.org/mondial/10/meta#unemployment": ["9.4"], "http://www.w3.org/1999/02/22-rdf-syntax-ns#type": ["http://www.semwebtech.org/mondial/10/meta#Country"], "http://www.w3.org/2000/01/rdf-schema#label": ["Greenland"], "http://www.w3.org/2004/02/skos/core#prefLabel": ["Kalaallit Nunaat"], "http://www.w3.org/ns/sosa/hasObservation": ["http://www.semwebtech.org/mondial/countries/GL_obeth1", "http://www.semwebtech.org/mondial/countries/GL_obeth2", "http://www.semwebtech.org/mondial/countries/GL_obpop", "http://www.semwebtech.org/mondial/countries/GL_obpophist0", "http://www.semwebtech.org/mondial/countries/GL_obpophist1", "http://www.semwebtech.org/mondial/countries/GL_obpophist2", "http://www.semwebtech.org/mondial/countries/GL_obpophist3", "http://www.semwebtech.org/mondial/countries/GL_obpophist4", "http://www.semwebtech.org/mondial/countries/GL_obpophist5", "http://www.semwebtech.org/mondial/countries/GL_obpophist6", "http://www.semwebtech.org/mondial/countries/GL_obpophist7", "http://www.semwebtech.org/mondial/countries/GL_obpophist8", "http://www.semwebtech.org/mondial/countries/GL_obpophist9", "http://www.semwebtech.org/mondial/countries/GL_obrel1", "http://www.semwebtech.org/mondial/countries/GL_obrel2", "http://www.semwebtech.org/mondial/countries/GL_obrel3"]}