{"http://rdfs.org/ns/void#inDataset": ["http://www.semwebtech.org/mondial/md_dataset"], "http://www.opengis.net/ont/geosparql#hasGeometry": ["http://www.semwebtech.org/mondial/countries/RC/cities/Jhongli_geom"], "http://www.semwebtech.org/mondial/10/meta#locatedOnIsland": ["http://www.semwebtech.org/mondial/islands/Taiwan"], "http://www.w3.org/1999/02/22-rdf-syntax-ns#type": ["http://www.semwebtech.org/mondial/10/meta#City"], "http://www.w3.org/2000/01/rdf-schema#label": ["Jhongli"], "http://www.w3.org/2004/02/skos/core#altLabel": ["Zhongli"], "http://www.w3.org/2004/02/skos/core#prefLabel": ["\u4e2d\u58e2\u5e02"], "http://www.w3.org/ns/sosa/hasObservation": ["http://www.semwebtech.org/mondial/countries/RC/cities/Jhongli_obpop", "http://www.semwebtech.org/mondial/countries/RC/cities/Jhongli_obpophist0", "http://www.semwebtech.org/mondial/countries/RC/cities/Jhongli_obpophist1", "http://www.semwebtech.org/mondial/countries/RC/cities/Jhongli_obpophist2", "http://www.semwebtech.org/mondial/countries/RC/cities/Jhongli_obpophist3"]}