{"http://rdfs.org/ns/void#inDataset": ["http://www.semwebtech.org/mondial/md_dataset"], "http://www.opengis.net/ont/geosparql#hasGeometry": ["http://www.semwebtech.org/mondial/countries/RSM_geom"], "http://www.opengis.net/ont/geosparql#hasMetricArea": ["60"], "http://www.semwebtech.org/mondial/10/meta#capital": ["http://www.semwebtech.org/mondial/countries/RSM/cities/San+Marino"], "http://www.semwebtech.org/mondial/10/meta#carCode": ["RSM"], "http://www.semwebtech.org/mondial/10/meta#gdpAgri": ["0.1"], "http://www.semwebtech.org/mondial/10/meta#gdpInd": ["39.2"], "http://www.semwebtech.org/mondial/10/meta#gdpServ": ["60.7"], "http://www.semwebtech.org/mondial/10/meta#gdpTotal": ["1866"], "http://www.semwebtech.org/mondial/10/meta#government": ["http://www.wikidata.org/entry/Q7270"], "http://www.semwebtech.org/mondial/10/meta#hasCity": ["http://www.semwebtech.org/mondial/countries/RSM/cities/San+Marino"], "http://www.semwebtech.org/mondial/10/meta#independenceDate": ["0301-01-01"], "http://www.semwebtech.org/mondial/10/meta#infantMortality": ["4.52"], "http://www.semwebtech.org/mondial/10/meta#neighbor": ["http://www.semwebtech.org/mondial/countries/I"], "http://www.semwebtech.org/mondial/10/meta#populationGrowth": ["0.87"], "http://www.semwebtech.org/mondial/10/meta#unemployment": ["7"], "http://www.w3.org/1999/02/22-rdf-syntax-ns#type": ["http://www.semwebtech.org/mondial/10/meta#Country"], "http://www.w3.org/2000/01/rdf-schema#label": ["San Marino"], "http://www.w3.org/2004/02/skos/core#prefLabel": ["Repubblica di San Marino (la)"], "http://www.w3.org/ns/sosa/hasObservation": ["http://www.semwebtech.org/mondial/countries/RSM_obeth1", "http://www.semwebtech.org/mondial/countries/RSM_obpop", "http://www.semwebtech.org/mondial/countries/RSM_obpophist0", "http://www.semwebtech.org/mondial/countries/RSM_obpophist1", "http://www.semwebtech.org/mondial/countries/RSM_obpophist2", "http://www.semwebtech.org/mondial/countries/RSM_obpophist3", "http://www.semwebtech.org/mondial/countries/RSM_obpophist4", "http://www.semwebtech.org/mondial/countries/RSM_obpophist5", "http://www.semwebtech.org/mondial/countries/RSM_obpophist6", "http://www.semwebtech.org/mondial/countries/RSM_obpophist7", "http://www.semwebtech.org/mondial/countries/RSM_obrel1", "http://www.semwebtech.org/mondial/countries/RSM_obrel2", "http://www.semwebtech.org/mondial/countries/RSM_obrel3"]}