{"http://rdfs.org/ns/void#inDataset": ["http://www.semwebtech.org/mondial/md_dataset"], "http://www.opengis.net/ont/geosparql#hasGeometry": ["http://www.semwebtech.org/mondial/countries/BY_geom"], "http://www.opengis.net/ont/geosparql#hasMetricArea": ["207600"], "http://www.semwebtech.org/mondial/10/meta#capital": ["http://www.semwebtech.org/mondial/countries/BY/provinces/Minsk+City/cities/Minsk"], "http://www.semwebtech.org/mondial/10/meta#carCode": ["BY"], "http://www.semwebtech.org/mondial/10/meta#gdpAgri": ["9.2"], "http://www.semwebtech.org/mondial/10/meta#gdpInd": ["46.2"], "http://www.semwebtech.org/mondial/10/meta#gdpServ": ["44.7"], "http://www.semwebtech.org/mondial/10/meta#gdpTotal": ["69240"], "http://www.semwebtech.org/mondial/10/meta#government": ["republic in name, although in fact a dictatorship"], "http://www.semwebtech.org/mondial/10/meta#hasCity": ["http://www.semwebtech.org/mondial/countries/BY/provinces/Brest/cities/Baranavichy", "http://www.semwebtech.org/mondial/countries/BY/provinces/Brest/cities/Brest", "http://www.semwebtech.org/mondial/countries/BY/provinces/Brest/cities/Pinsk", "http://www.semwebtech.org/mondial/countries/BY/provinces/Gomel/cities/Gomel", "http://www.semwebtech.org/mondial/countries/BY/provinces/Gomel/cities/Mazyr", "http://www.semwebtech.org/mondial/countries/BY/provinces/Grodno/cities/Grodno", "http://www.semwebtech.org/mondial/countries/BY/provinces/Mahiljou/cities/Bobruysk", "http://www.semwebtech.org/mondial/countries/BY/provinces/Mahiljou/cities/Mahiljou", "http://www.semwebtech.org/mondial/countries/BY/provinces/Minsk+City/cities/Minsk", "http://www.semwebtech.org/mondial/countries/BY/provinces/Minsk/cities/Barysaw", "http://www.semwebtech.org/mondial/countries/BY/provinces/Vitebsk/cities/Novopolotsk", "http://www.semwebtech.org/mondial/countries/BY/provinces/Vitebsk/cities/Orsha", "http://www.semwebtech.org/mondial/countries/BY/provinces/Vitebsk/cities/Vitebsk"], "http://www.semwebtech.org/mondial/10/meta#hasProvince": ["http://www.semwebtech.org/mondial/countries/BY/provinces/Brest", "http://www.semwebtech.org/mondial/countries/BY/provinces/Gomel", "http://www.semwebtech.org/mondial/countries/BY/provinces/Grodno", "http://www.semwebtech.org/mondial/countries/BY/provinces/Mahiljou", "http://www.semwebtech.org/mondial/countries/BY/provinces/Minsk", "http://www.semwebtech.org/mondial/countries/BY/provinces/Minsk+City", "http://www.semwebtech.org/mondial/countries/BY/provinces/Vitebsk"], "http://www.semwebtech.org/mondial/10/meta#independenceDate": ["1991-08-25"], "http://www.semwebtech.org/mondial/10/meta#infantMortality": ["3.64"], "http://www.semwebtech.org/mondial/10/meta#neighbor": ["http://www.semwebtech.org/mondial/countries/LT", "http://www.semwebtech.org/mondial/countries/LV", "http://www.semwebtech.org/mondial/countries/PL", "http://www.semwebtech.org/mondial/countries/R", "http://www.semwebtech.org/mondial/countries/UA"], "http://www.semwebtech.org/mondial/10/meta#populationGrowth": ["-0.19"], "http://www.semwebtech.org/mondial/10/meta#unemployment": ["1"], "http://www.semwebtech.org/mondial/10/meta#wasDependentOf": ["http://www.semwebtech.org/mondial/politicalbodies/Soviet+Union"], "http://www.w3.org/1999/02/22-rdf-syntax-ns#type": ["http://www.semwebtech.org/mondial/10/meta#Country"], "http://www.w3.org/2000/01/rdf-schema#label": ["Belarus"], "http://www.w3.org/2004/02/skos/core#prefLabel": ["\u0420\u044d\u0441\u043f\u0443\u0431\u043b\u0456\u043a\u0430 \u0411\u0435\u043b\u0430\u0440\u0443\u0441\u044c"], "http://www.w3.org/ns/sosa/hasObservation": ["http://www.semwebtech.org/mondial/countries/BY_obeth1", "http://www.semwebtech.org/mondial/countries/BY_obeth2", "http://www.semwebtech.org/mondial/countries/BY_obeth3", "http://www.semwebtech.org/mondial/countries/BY_obeth4", "http://www.semwebtech.org/mondial/countries/BY_obeth5", "http://www.semwebtech.org/mondial/countries/BY_obpop", "http://www.semwebtech.org/mondial/countries/BY_obpophist0", "http://www.semwebtech.org/mondial/countries/BY_obpophist1", "http://www.semwebtech.org/mondial/countries/BY_obpophist2", "http://www.semwebtech.org/mondial/countries/BY_obpophist3", "http://www.semwebtech.org/mondial/countries/BY_obpophist4", "http://www.semwebtech.org/mondial/countries/BY_obpophist5", "http://www.semwebtech.org/mondial/countries/BY_obpophist6", "http://www.semwebtech.org/mondial/countries/BY_obrel1", "http://www.semwebtech.org/mondial/countries/BY_obrel2", "http://www.semwebtech.org/mondial/countries/BY_obrel3", "http://www.semwebtech.org/mondial/countries/BY_obrel4"]}